{"datetime": "11:04:36 01-04-2021", "maxk": 2571257, "anims": [{"id": "99012315", "lon": 107582572, "lat": 51850479, "dir": 306, "lasttime": "01.09.2021 03:03:49", "gos_num": "т55", "rid": 8, "rnum": "2", "rtype": "Тр", "low_floor": "0"}, {"id": "33136953", "lon": 107625624, "lat": 51820177, "dir": 243, "lasttime": "01.09.2021 03:04:05", "gos_num": "т51", "rid": 9, "rnum": "4", "rtype": "Тр", "low_floor": "0"}, {"id": "33121607", "lon": 107625593, "lat": 51843426, "dir": 158, "lasttime": "01.09.2021 03:04:03", "gos_num": "т38", "rid": 9, "rnum": "4", "rtype": "Тр", "low_floor": "0"}, {"id": "33137004", "lon": 107600254, "lat": 51809045, "dir": 270, "lasttime": "01.09.2021 03:04:05", "gos_num": "т92", "rid": 1, "rnum": "1", "rtype": "Тр", "low_floor": "0"}, {"id": "33121655", "lon": 107580819, "lat": 51847507, "dir": 135, "lasttime": "01.09.2021 03:04:08", "gos_num": "т25", "rid": 1, "rnum": "1", "rtype": "Тр", "low_floor": "0"}, {"id": "33136806", "lon": 107678699, "lat": 51822348, "dir": 88, "lasttime": "01.09.2021 03:03:50", "gos_num": "т11", "rid": 10, "rnum": "4", "rtype": "Тр", "low_floor": "0"}, {"id": "99012304", "lon": 107580276, "lat": 51848087, "dir": 405, "lasttime": "01.09.2021 03:04:01", "gos_num": "т49", "rid": 1, "rnum": "1", "rtype": "Тр", "low_floor": "0"}, {"id": "99012321", "lon": 107595321, "lat": 51837474, "dir": 237, "lasttime": "01.09.2021 03:03:37", "gos_num": "т86", "rid": 8, "rnum": "2", "rtype": "Тр", "low_floor": "0"}, {"id": "99012308", "lon": 107576057, "lat": 51854312, "dir": 134, "lasttime": "01.09.2021 03:00:37", "gos_num": "т53", "rid": 8, "rnum": "2", "rtype": "Тр", "low_floor": "0"}, {"id": "99012301", "lon": 107613441, "lat": 51809051, "dir": 268, "lasttime": "01.09.2021 03:03:38", "gos_num": "т19", "rid": 10, "rnum": "4", "rtype": "Тр", "low_floor": "0"}, {"id": "99012397", "lon": 107575081, "lat": 51854881, "dir": 133, "lasttime": "01.09.2021 03:03:31", "gos_num": "т93", "rid": 1, "rnum": "1", "rtype": "Тр", "low_floor": "0"}, {"id": "99012491", "lon": 107575468, "lat": 51854568, "dir": 132, "lasttime": "01.09.2021 03:03:58", "gos_num": "т91", "rid": 8, "rnum": "2", "rtype": "Тр", "low_floor": "0"}, {"id": "99012332", "lon": 107617469, "lat": 51809078, "dir": 118, "lasttime": "01.09.2021 03:03:41", "gos_num": "т77", "rid": 8, "rnum": "2", "rtype": "Тр", "low_floor": "0"}, {"id": "99012306", "lon": 107654144, "lat": 51812252, "dir": 52, "lasttime": "01.09.2021 03:03:45", "gos_num": "т33", "rid": 8, "rnum": "2", "rtype": "Тр", "low_floor": "0"}, {"id": "99012399", "lon": 107587295, "lat": 51831401, "dir": 357, "lasttime": "01.09.2021 03:03:58", "gos_num": "т36", "rid": 10, "rnum": "4", "rtype": "Тр", "low_floor": "0"}, {"id": "99012434", "lon": 107595141, "lat": 51814166, "dir": 349, "lasttime": "01.09.2021 03:04:04", "gos_num": "т34", "rid": 10, "rnum": "4", "rtype": "Тр", "low_floor": "0"}, {"id": "99012429", "lon": 107589764, "lat": 51827253, "dir": 112, "lasttime": "01.09.2021 03:04:05", "gos_num": "т29", "rid": 8, "rnum": "2", "rtype": "Тр", "low_floor": "0"}, {"id": "99012490", "lon": 107644469, "lat": 51821741, "dir": 269, "lasttime": "01.09.2021 03:04:07", "gos_num": "т90", "rid": 10, "rnum": "4", "rtype": "Тр", "low_floor": "0"}, {"id": "47015076", "lon": 107678316, "lat": 51822878, "dir": 213, "lasttime": "01.09.2021 03:04:02", "gos_num": "т05", "rid": 10, "rnum": "4", "rtype": "Тр", "low_floor": "0"}, {"id": "33137020", "lon": 107594993, "lat": 51838262, "dir": 322, "lasttime": "01.09.2021 03:03:59", "gos_num": "т85", "rid": 1, "rnum": "1", "rtype": "Тр", "low_floor": "0"}, {"id": "33121614", "lon": 107678864, "lat": 51822757, "dir": 322, "lasttime": "01.09.2021 03:03:45", "gos_num": "т94", "rid": 10, "rnum": "4", "rtype": "Тр", "low_floor": "0"}, {"id": "47015075", "lon": 107591501, "lat": 51840966, "dir": 314, "lasttime": "01.09.2021 03:03:35", "gos_num": "т04", "rid": 8, "rnum": "2", "rtype": "Тр", "low_floor": "0"}, {"id": "33137180", "lon": 107678953, "lat": 51822543, "dir": 0, "lasttime": "01.09.2021 03:03:44", "gos_num": "т97", "rid": 10, "rnum": "4", "rtype": "Тр", "low_floor": "0"}, {"id": "33001891", "lon": 107653551, "lat": 51811886, "dir": 228, "lasttime": "01.09.2021 03:03:59", "gos_num": "т83", "rid": 1, "rnum": "1", "rtype": "Тр", "low_floor": "0"}, {"id": "33136724", "lon": 107643490, "lat": 51842297, "dir": 264, "lasttime": "01.09.2021 03:04:04", "gos_num": "т78", "rid": 8, "rnum": "2", "rtype": "Тр", "low_floor": "0"}, {"id": "33136866", "lon": 107645371, "lat": 51821741, "dir": 88, "lasttime": "01.09.2021 03:03:58", "gos_num": "т80", "rid": 9, "rnum": "4", "rtype": "Тр", "low_floor": "0"}, {"id": "47015084", "lon": 107611803, "lat": 51841545, "dir": 446, "lasttime": "01.09.2021 03:04:00", "gos_num": "т14", "rid": 1, "rnum": "1", "rtype": "Тр", "low_floor": "0"}, {"id": "99012387", "lon": 107643524, "lat": 51842211, "dir": 104, "lasttime": "01.09.2021 03:03:40", "gos_num": "т87", "rid": 1, "rnum": "1", "rtype": "Тр", "low_floor": "0"}, {"id": "47015079", "lon": 107584195, "lat": 51845298, "dir": 139, "lasttime": "01.09.2021 03:04:00", "gos_num": "т08", "rid": 8, "rnum": "2", "rtype": "Тр", "low_floor": "0"}, {"id": "47015074", "lon": 107608843, "lat": 51809088, "dir": 75, "lasttime": "01.09.2021 03:03:36", "gos_num": "т03", "rid": 9, "rnum": "4", "rtype": "Тр", "low_floor": "1"}, {"id": "47015072", "lon": 107676898, "lat": 51823501, "dir": 271, "lasttime": "01.09.2021 03:03:56", "gos_num": "т01", "rid": 10, "rnum": "4", "rtype": "Тр", "low_floor": "1"}, {"id": "99012430", "lon": 107586959, "lat": 51833106, "dir": 178, "lasttime": "01.09.2021 03:04:09", "gos_num": "т30", "rid": 9, "rnum": "4", "rtype": "Тр", "low_floor": "0"}, {"id": "33137315", "lon": 107623897, "lat": 51817086, "dir": 175, "lasttime": "01.09.2021 03:03:56", "gos_num": "т72", "rid": 10, "rnum": "4", "rtype": "Тр", "low_floor": "0"}]}