{"datetime": "21:14:54 01-14-2021", "maxk": 3555345, "anims": [{"id": "99012315", "lon": 107575828, "lat": 51854454, "dir": 315, "lasttime": "01.09.2021 13:13:36", "gos_num": "т55", "rid": 8, "rnum": "2", "rtype": "Тр", "low_floor": "0"}, {"id": "33137004", "lon": 107602902, "lat": 51809146, "dir": 299, "lasttime": "01.09.2021 13:14:38", "gos_num": "т92", "rid": 1, "rnum": "1", "rtype": "Тр", "low_floor": "0"}, {"id": "33136806", "lon": 107598978, "lat": 51809057, "dir": 90, "lasttime": "01.09.2021 13:14:37", "gos_num": "т11", "rid": 9, "rnum": "4", "rtype": "Тр", "low_floor": "0"}, {"id": "99012328", "lon": 107657157, "lat": 51820949, "dir": 182, "lasttime": "01.09.2021 13:14:20", "gos_num": "т40", "rid": 1, "rnum": "1", "rtype": "Тр", "low_floor": "0"}, {"id": "99012303", "lon": 107581611, "lat": 51848964, "dir": 225, "lasttime": "01.09.2021 13:14:08", "gos_num": "т21", "rid": 8, "rnum": "2", "rtype": "Тр", "low_floor": "0"}, {"id": "99012308", "lon": 107626045, "lat": 51807849, "dir": 100, "lasttime": "01.09.2021 13:14:27", "gos_num": "т53", "rid": 8, "rnum": "2", "rtype": "Тр", "low_floor": "0"}, {"id": "99012301", "lon": 107592048, "lat": 51823772, "dir": 335, "lasttime": "01.09.2021 13:14:27", "gos_num": "т19", "rid": 10, "rnum": "4", "rtype": "Тр", "low_floor": "0"}, {"id": "99012397", "lon": 107648389, "lat": 51809573, "dir": 239, "lasttime": "01.09.2021 13:14:15", "gos_num": "т93", "rid": 1, "rnum": "1", "rtype": "Тр", "low_floor": "0"}, {"id": "99012302", "lon": 107632751, "lat": 51821582, "dir": 86, "lasttime": "01.09.2021 13:13:45", "gos_num": "т45", "rid": 9, "rnum": "4", "rtype": "Тр", "low_floor": "0"}, {"id": "99012491", "lon": 107657464, "lat": 51819088, "dir": 363, "lasttime": "01.09.2021 13:14:29", "gos_num": "т91", "rid": 8, "rnum": "2", "rtype": "Тр", "low_floor": "0"}, {"id": "99012429", "lon": 107604476, "lat": 51841211, "dir": 267, "lasttime": "01.09.2021 13:14:15", "gos_num": "т29", "rid": 8, "rnum": "2", "rtype": "Тр", "low_floor": "0"}, {"id": "99012490", "lon": 107623019, "lat": 51812821, "dir": 203, "lasttime": "01.09.2021 13:14:24", "gos_num": "т90", "rid": 10, "rnum": "4", "rtype": "Тр", "low_floor": "0"}, {"id": "33137020", "lon": 107638764, "lat": 51842097, "dir": 444, "lasttime": "01.09.2021 13:14:38", "gos_num": "т85", "rid": 1, "rnum": "1", "rtype": "Тр", "low_floor": "0"}, {"id": "33121614", "lon": 107678413, "lat": 51822853, "dir": 196, "lasttime": "01.09.2021 13:14:31", "gos_num": "т94", "rid": 10, "rnum": "4", "rtype": "Тр", "low_floor": "0"}, {"id": "99012330", "lon": 107584182, "lat": 51845325, "dir": 143, "lasttime": "01.09.2021 13:14:12", "gos_num": "т89", "rid": 1, "rnum": "1", "rtype": "Тр", "low_floor": "0"}, {"id": "33001891", "lon": 107575303, "lat": 51854735, "dir": 137, "lasttime": "01.09.2021 13:14:37", "gos_num": "т83", "rid": 1, "rnum": "1", "rtype": "Тр", "low_floor": "0"}, {"id": "33136866", "lon": 107604650, "lat": 51841252, "dir": 268, "lasttime": "01.09.2021 13:14:30", "gos_num": "т80", "rid": 9, "rnum": "4", "rtype": "Тр", "low_floor": "0"}, {"id": "47015084", "lon": 107636276, "lat": 51805746, "dir": 280, "lasttime": "01.09.2021 13:14:00", "gos_num": "т14", "rid": 1, "rnum": "1", "rtype": "Тр", "low_floor": "0"}, {"id": "99012387", "lon": 107595126, "lat": 51838143, "dir": 317, "lasttime": "01.09.2021 13:14:20", "gos_num": "т87", "rid": 1, "rnum": "1", "rtype": "Тр", "low_floor": "0"}, {"id": "47015079", "lon": 107657976, "lat": 51824410, "dir": 358, "lasttime": "01.09.2021 13:14:38", "gos_num": "т08", "rid": 8, "rnum": "2", "rtype": "Тр", "low_floor": "0"}, {"id": "47015074", "lon": 107613621, "lat": 51841638, "dir": 409, "lasttime": "01.09.2021 13:14:25", "gos_num": "т03", "rid": 10, "rnum": "4", "rtype": "Тр", "low_floor": "1"}, {"id": "47015072", "lon": 107660518, "lat": 51821016, "dir": 326, "lasttime": "01.09.2021 13:14:31", "gos_num": "т01", "rid": 10, "rnum": "4", "rtype": "Тр", "low_floor": "1"}, {"id": "47015087", "lon": 107589615, "lat": 51827403, "dir": 150, "lasttime": "01.09.2021 13:14:08", "gos_num": "т16", "rid": 8, "rnum": "2", "rtype": "Тр", "low_floor": "0"}]}