{"datetime": "13:30:13 18-30-2021", "maxk": 18294030, "anims": [{"id": "99012461", "lon": 107650808, "lat": 51821808, "dir": 99, "lasttime": "18.11.2021 05:28:46", "gos_num": "т61", "rid": 14, "rnum": "8", "rtype": "Тр", "low_floor": "0"}, {"id": "99012332", "lon": 107633071, "lat": 51821613, "dir": 271, "lasttime": "18.11.2021 05:29:21", "gos_num": "т77", "rid": 10, "rnum": "4", "rtype": "Тр", "low_floor": "0"}, {"id": "99012310", "lon": 107656974, "lat": 51814018, "dir": 363, "lasttime": "18.11.2021 05:29:28", "gos_num": "т79", "rid": 8, "rnum": "2", "rtype": "Тр", "low_floor": "0"}, {"id": "99012438", "lon": 107601081, "lat": 51840119, "dir": 53, "lasttime": "18.11.2021 05:29:24", "gos_num": "т38", "rid": 1, "rnum": "1", "rtype": "Тр", "low_floor": "0"}, {"id": "99012397", "lon": 107607974, "lat": 51809083, "dir": 270, "lasttime": "18.11.2021 05:28:43", "gos_num": "т93", "rid": 1, "rnum": "1", "rtype": "Тр", "low_floor": "0"}, {"id": "99012352", "lon": 107658158, "lat": 51826721, "dir": 175, "lasttime": "18.11.2021 05:29:35", "gos_num": "т52", "rid": 1, "rnum": "1", "rtype": "Тр", "low_floor": "0"}, {"id": "99012317", "lon": 107603225, "lat": 51809082, "dir": 271, "lasttime": "18.11.2021 05:29:01", "gos_num": "т39", "rid": 13, "rnum": "7", "rtype": "Тр", "low_floor": "0"}, {"id": "99012430", "lon": 107644669, "lat": 51807964, "dir": 48, "lasttime": "18.11.2021 05:29:36", "gos_num": "т30", "rid": 8, "rnum": "2", "rtype": "Тр", "low_floor": "0"}, {"id": "99012321", "lon": 107595733, "lat": 51812004, "dir": 170, "lasttime": "18.11.2021 05:29:27", "gos_num": "т86", "rid": 8, "rnum": "2", "rtype": "Тр", "low_floor": "0"}, {"id": "99012480", "lon": 107644284, "lat": 51821761, "dir": 269, "lasttime": "18.11.2021 05:29:14", "gos_num": "т80", "rid": 13, "rnum": "7", "rtype": "Тр", "low_floor": "0"}, {"id": "99012306", "lon": 107620246, "lat": 51843933, "dir": 290, "lasttime": "18.11.2021 05:29:15", "gos_num": "т33", "rid": 9, "rnum": "4", "rtype": "Тр", "low_floor": "0"}, {"id": "99012308", "lon": 107599685, "lat": 51839477, "dir": 231, "lasttime": "18.11.2021 05:29:25", "gos_num": "т53", "rid": 14, "rnum": "8", "rtype": "Тр", "low_floor": "0"}, {"id": "99012490", "lon": 107587319, "lat": 51831469, "dir": 359, "lasttime": "18.11.2021 05:29:33", "gos_num": "т90", "rid": 13, "rnum": "7", "rtype": "Тр", "low_floor": "0"}, {"id": "99012303", "lon": 107678451, "lat": 51822990, "dir": 206, "lasttime": "18.11.2021 05:29:08", "gos_num": "т21", "rid": 10, "rnum": "4", "rtype": "Тр", "low_floor": "0"}, {"id": "99012448", "lon": 107670784, "lat": 51822251, "dir": 245, "lasttime": "18.11.2021 05:29:35", "gos_num": "т48", "rid": 10, "rnum": "4", "rtype": "Тр", "low_floor": "0"}, {"id": "99012497", "lon": 107575101, "lat": 51854871, "dir": 135, "lasttime": "18.11.2021 05:29:20", "gos_num": "т97", "rid": 1, "rnum": "1", "rtype": "Тр", "low_floor": "0"}, {"id": "99012318", "lon": 107595123, "lat": 51838134, "dir": 321, "lasttime": "18.11.2021 05:29:20", "gos_num": "т43", "rid": 8, "rnum": "2", "rtype": "Тр", "low_floor": "0"}, {"id": "99012315", "lon": 107598075, "lat": 51838775, "dir": 239, "lasttime": "18.11.2021 05:29:20", "gos_num": "т55", "rid": 8, "rnum": "2", "rtype": "Тр", "low_floor": "0"}, {"id": "99013050", "lon": 107644614, "lat": 51821763, "dir": 86, "lasttime": "18.11.2021 05:29:36", "gos_num": "т50", "rid": 9, "rnum": "4", "rtype": "Тр", "low_floor": "0"}, {"id": "99012307", "lon": 107596984, "lat": 51838169, "dir": 51, "lasttime": "18.11.2021 05:29:08", "gos_num": "т22", "rid": 10, "rnum": "4", "rtype": "Тр", "low_floor": "0"}, {"id": "99012301", "lon": 107583129, "lat": 51846126, "dir": 135, "lasttime": "18.11.2021 05:29:06", "gos_num": "т19", "rid": 1, "rnum": "1", "rtype": "Тр", "low_floor": "0"}, {"id": "99012478", "lon": 107623128, "lat": 51812824, "dir": 15, "lasttime": "18.11.2021 05:29:34", "gos_num": "т78", "rid": 9, "rnum": "4", "rtype": "Тр", "low_floor": "0"}, {"id": "99012326", "lon": 107582977, "lat": 51849735, "dir": 44, "lasttime": "18.11.2021 05:29:29", "gos_num": "т74", "rid": 8, "rnum": "2", "rtype": "Тр", "low_floor": "0"}, {"id": "47015072", "lon": 107647451, "lat": 51841701, "dir": 279, "lasttime": "18.11.2021 05:29:36", "gos_num": "т01", "rid": 14, "rnum": "8", "rtype": "Тр", "low_floor": "1"}, {"id": "47015076", "lon": 107590743, "lat": 51841313, "dir": 337, "lasttime": "18.11.2021 05:29:18", "gos_num": "т05", "rid": 1, "rnum": "1", "rtype": "Тр", "low_floor": "1"}, {"id": "99012485", "lon": 107622726, "lat": 51812359, "dir": 203, "lasttime": "18.11.2021 05:27:13", "gos_num": "т85", "rid": 13, "rnum": "7", "rtype": "Тр", "low_floor": "0"}, {"id": "47015087", "lon": 107640315, "lat": 51805310, "dir": 279, "lasttime": "18.11.2021 05:29:21", "gos_num": "т16", "rid": 1, "rnum": "1", "rtype": "Тр", "low_floor": "1"}, {"id": "99012491", "lon": 107598064, "lat": 51809411, "dir": 319, "lasttime": "18.11.2021 05:29:09", "gos_num": "т91", "rid": 1, "rnum": "1", "rtype": "Тр", "low_floor": "0"}, {"id": "47015075", "lon": 107589665, "lat": 51827266, "dir": 153, "lasttime": "18.11.2021 05:29:19", "gos_num": "т04", "rid": 14, "rnum": "8", "rtype": "Тр", "low_floor": "1"}, {"id": "47015073", "lon": 107623115, "lat": 51812790, "dir": 18, "lasttime": "18.11.2021 05:29:13", "gos_num": "т02", "rid": 14, "rnum": "8", "rtype": "Тр", "low_floor": "1"}, {"id": "47015077", "lon": 107618491, "lat": 51841516, "dir": 93, "lasttime": "18.11.2021 05:29:19", "gos_num": "т06", "rid": 1, "rnum": "1", "rtype": "Тр", "low_floor": "1"}, {"id": "99013032", "lon": 107633616, "lat": 51841876, "dir": 193, "lasttime": "18.11.2021 05:29:37", "gos_num": "т32", "rid": 13, "rnum": "7", "rtype": "Тр", "low_floor": "0"}, {"id": "47015083", "lon": 107593841, "lat": 51839221, "dir": 141, "lasttime": "18.11.2021 05:29:14", "gos_num": "т13", "rid": 1, "rnum": "1", "rtype": "Тр", "low_floor": "1"}, {"id": "99012330", "lon": 107595436, "lat": 51837924, "dir": 137, "lasttime": "18.11.2021 05:29:11", "gos_num": "т89", "rid": 8, "rnum": "2", "rtype": "Тр", "low_floor": "0"}, {"id": "47015079", "lon": 107653680, "lat": 51836701, "dir": 159, "lasttime": "18.11.2021 05:29:11", "gos_num": "т08", "rid": 13, "rnum": "7", "rtype": "Тр", "low_floor": "1"}, {"id": "47015080", "lon": 107598263, "lat": 51809308, "dir": 124, "lasttime": "18.11.2021 05:29:31", "gos_num": "т09", "rid": 14, "rnum": "8", "rtype": "Тр", "low_floor": "1"}, {"id": "99012488", "lon": 107595176, "lat": 51814189, "dir": 349, "lasttime": "18.11.2021 05:28:49", "gos_num": "т88", "rid": 10, "rnum": "4", "rtype": "Тр", "low_floor": "0"}, {"id": "99012442", "lon": 107596663, "lat": 51810358, "dir": 135, "lasttime": "18.11.2021 05:29:27", "gos_num": "т42", "rid": 9, "rnum": "4", "rtype": "Тр", "low_floor": "0"}, {"id": "99012329", "lon": 107597679, "lat": 51838562, "dir": 234, "lasttime": "18.11.2021 05:27:54", "gos_num": "т44", "rid": 9, "rnum": "4", "rtype": "Тр", "low_floor": "0"}, {"id": "47015086", "lon": 107639478, "lat": 51842141, "dir": 264, "lasttime": "18.11.2021 05:29:01", "gos_num": "т15", "rid": 8, "rnum": "2", "rtype": "Тр", "low_floor": "1"}]}