[
  {
    "lat": 51855019,
    "lng": 107574796
  },
  {
    "lat": 51854690,
    "lng": 107575369
  },
  {
    "lat": 51854217,
    "lng": 107576129
  },
  {
    "lat": 51853335,
    "lng": 107577542
  },
  {
    "lat": 51852865,
    "lng": 107578307
  },
  {
    "lat": 51852190,
    "lng": 107579435
  },
  {
    "lat": 51851732,
    "lng": 107580206
  },
  {
    "lat": 51851268,
    "lng": 107580979
  },
  {
    "lat": 51850811,
    "lng": 107581751
  },
  {
    "lat": 51850066,
    "lng": 107583000
  },
  {
    "lat": 51849962,
    "lng": 107583061
  },
  {
    "lat": 51849868,
    "lng": 107583056
  },
  {
    "lat": 51849399,
    "lng": 107582299
  },
  {
    "lat": 51848935,
    "lng": 107581547
  },
  {
    "lat": 51848040,
    "lng": 107580122
  },
  {
    "lat": 51847932,
    "lng": 107580082
  },
  {
    "lat": 51847819,
    "lng": 107580133
  },
  {
    "lat": 51847351,
    "lng": 107580893
  },
  {
    "lat": 51846887,
    "lng": 107581644
  },
  {
    "lat": 51846417,
    "lng": 107582406
  },
  {
    "lat": 51845946,
    "lng": 107583168
  },
  {
    "lat": 51845154,
    "lng": 107584441
  },
  {
    "lat": 51845107,
    "lng": 107584504
  },
  {
    "lat": 51844780,
    "lng": 107584946
  },
  {
    "lat": 51844253,
    "lng": 107585728
  },
  {
    "lat": 51843643,
    "lng": 107586788
  },
  {
    "lat": 51843447,
    "lng": 107587107
  },
  {
    "lat": 51842627,
    "lng": 107588437
  },
  {
    "lat": 51841797,
    "lng": 107589754
  },
  {
    "lat": 51841346,
    "lng": 107590538
  },
  {
    "lat": 51840895,
    "lng": 107591321
  },
  {
    "lat": 51840372,
    "lng": 107592205
  },
  {
    "lat": 51840187,
    "lng": 107592500
  },
  {
    "lat": 51839925,
    "lng": 107592886
  },
  {
    "lat": 51839397,
    "lng": 107593532
  },
  {
    "lat": 51838867,
    "lng": 107594175
  },
  {
    "lat": 51838022,
    "lng": 107595208
  },
  {
    "lat": 51837705,
    "lng": 107595594
  },
  {
    "lat": 51837634,
    "lng": 107595773
  },
  {
    "lat": 51837655,
    "lng": 107595906
  },
  {
    "lat": 51837716,
    "lng": 107596032
  },
  {
    "lat": 51837747,
    "lng": 107596090
  },
  {
    "lat": 51838485,
    "lng": 107597619
  },
  {
    "lat": 51838976,
    "lng": 107598642
  },
  {
    "lat": 51839357,
    "lng": 107599438
  },
  {
    "lat": 51839768,
    "lng": 107600291
  },
  {
    "lat": 51840173,
    "lng": 107601138
  },
  {
    "lat": 51840954,
    "lng": 107602755
  },
  {
    "lat": 51841101,
    "lng": 107603110
  },
  {
    "lat": 51841115,
    "lng": 107603190
  },
  {
    "lat": 51841131,
    "lng": 107603277
  },
  {
    "lat": 51841145,
    "lng": 107603356
  },
  {
    "lat": 51841183,
    "lng": 107604177
  },
  {
    "lat": 51841227,
    "lng": 107605247
  },
  {
    "lat": 51841273,
    "lng": 107606320
  },
  {
    "lat": 51841319,
    "lng": 107607383
  },
  {
    "lat": 51841366,
    "lng": 107608455
  },
  {
    "lat": 51841412,
    "lng": 107609528
  },
  {
    "lat": 51841459,
    "lng": 107610601
  },
  {
    "lat": 51841577,
    "lng": 107612379
  },
  {
    "lat": 51841631,
    "lng": 107613627
  },
  {
    "lat": 51841650,
    "lng": 107613995
  },
  {
    "lat": 51841644,
    "lng": 107615411
  },
  {
    "lat": 51841611,
    "lng": 107616481
  },
  {
    "lat": 51841578,
    "lng": 107617553
  },
  {
    "lat": 51841538,
    "lng": 107618626
  },
  {
    "lat": 51841505,
    "lng": 107619689
  },
  {
    "lat": 51841472,
    "lng": 107620761
  },
  {
    "lat": 51841439,
    "lng": 107621834
  },
  {
    "lat": 51841399,
    "lng": 107622907
  },
  {
    "lat": 51841324,
    "lng": 107624985
  },
  {
    "lat": 51841346,
    "lng": 107626061
  },
  {
    "lat": 51841380,
    "lng": 107627187
  },
  {
    "lat": 51841445,
    "lng": 107628250
  },
  {
    "lat": 51841518,
    "lng": 107629323
  },
  {
    "lat": 51841585,
    "lng": 107630385
  },
  {
    "lat": 51841659,
    "lng": 107631574
  },
  {
    "lat": 51841717,
    "lng": 107632649
  },
  {
    "lat": 51841790,
    "lng": 107633852
  },
  {
    "lat": 51841856,
    "lng": 107634913
  },
  {
    "lat": 51841931,
    "lng": 107636069
  },
  {
    "lat": 51841996,
    "lng": 107637134
  },
  {
    "lat": 51842069,
    "lng": 107638206
  },
  {
    "lat": 51842135,
    "lng": 107639269
  },
  {
    "lat": 51842208,
    "lng": 107640342
  },
  {
    "lat": 51842267,
    "lng": 107641523
  },
  {
    "lat": 51842269,
    "lng": 107642946
  },
  {
    "lat": 51842207,
    "lng": 107643706
  },
  {
    "lat": 51842121,
    "lng": 107644341
  },
  {
    "lat": 51841849,
    "lng": 107646155
  },
  {
    "lat": 51841581,
    "lng": 107647974
  },
  {
    "lat": 51841419,
    "lng": 107649010
  },
  {
    "lat": 51841260,
    "lng": 107650051
  },
  {
    "lat": 51841087,
    "lng": 107651215
  },
  {
    "lat": 51840975,
    "lng": 107651634
  },
  {
    "lat": 51840753,
    "lng": 107651819
  },
  {
    "lat": 51840113,
    "lng": 107652100
  },
  {
    "lat": 51839477,
    "lng": 107652379
  },
  {
    "lat": 51838474,
    "lng": 107652838
  },
  {
    "lat": 51837839,
    "lng": 107653141
  },
  {
    "lat": 51837203,
    "lng": 107653431
  },
  {
    "lat": 51836566,
    "lng": 107653731
  },
  {
    "lat": 51835923,
    "lng": 107654021
  },
  {
    "lat": 51835287,
    "lng": 107654321
  },
  {
    "lat": 51834650,
    "lng": 107654611
  },
  {
    "lat": 51834014,
    "lng": 107654911
  },
  {
    "lat": 51833378,
    "lng": 107655212
  },
  {
    "lat": 51832444,
    "lng": 107655652
  },
  {
    "lat": 51831806,
    "lng": 107655952
  },
  {
    "lat": 51830873,
    "lng": 107656376
  },
  {
    "lat": 51830592,
    "lng": 107656501
  },
  {
    "lat": 51829692,
    "lng": 107656903
  },
  {
    "lat": 51828649,
    "lng": 107657376
  },
  {
    "lat": 51828007,
    "lng": 107657658
  },
  {
    "lat": 51827154,
    "lng": 107658010
  },
  {
    "lat": 51826805,
    "lng": 107658107
  },
  {
    "lat": 51826397,
    "lng": 107658130
  },
  {
    "lat": 51825798,
    "lng": 107658089
  },
  {
    "lat": 51825136,
    "lng": 107658033
  },
  {
    "lat": 51824473,
    "lng": 107657980
  },
  {
    "lat": 51823810,
    "lng": 107657915
  },
  {
    "lat": 51823153,
    "lng": 107657862
  },
  {
    "lat": 51822267,
    "lng": 107657753
  },
  {
    "lat": 51821715,
    "lng": 107657670
  },
  {
    "lat": 51821537,
    "lng": 107657590
  },
  {
    "lat": 51821398,
    "lng": 107657326
  },
  {
    "lat": 51821292,
    "lng": 107657138
  },
  {
    "lat": 51821211,
    "lng": 107657072
  },
  {
    "lat": 51821068,
    "lng": 107657042
  },
  {
    "lat": 51820970,
    "lng": 107657079
  },
  {
    "lat": 51820836,
    "lng": 107657233
  },
  {
    "lat": 51820664,
    "lng": 107657494
  },
  {
    "lat": 51820003,
    "lng": 107657465
  },
  {
    "lat": 51819340,
    "lng": 107657422
  },
  {
    "lat": 51818677,
    "lng": 107657390
  },
  {
    "lat": 51818013,
    "lng": 107657347
  },
  {
    "lat": 51817350,
    "lng": 107657315
  },
  {
    "lat": 51816687,
    "lng": 107657272
  },
  {
    "lat": 51816024,
    "lng": 107657239
  },
  {
    "lat": 51814900,
    "lng": 107657153
  },
  {
    "lat": 51814378,
    "lng": 107657045
  },
  {
    "lat": 51813819,
    "lng": 107656723
  },
  {
    "lat": 51813441,
    "lng": 107656208
  },
  {
    "lat": 51812999,
    "lng": 107655416
  },
  {
    "lat": 51812228,
    "lng": 107654006
  },
  {
    "lat": 51811406,
    "lng": 107652545
  },
  {
    "lat": 51811029,
    "lng": 107651660
  },
  {
    "lat": 51810645,
    "lng": 107650781
  },
  {
    "lat": 51810266,
    "lng": 107649901
  },
  {
    "lat": 51809716,
    "lng": 107648655
  },
  {
    "lat": 51809338,
    "lng": 107647777
  },
  {
    "lat": 51808953,
    "lng": 107646897
  },
  {
    "lat": 51808575,
    "lng": 107646017
  },
  {
    "lat": 51808102,
    "lng": 107644985
  },
  {
    "lat": 51807761,
    "lng": 107644391
  },
  {
    "lat": 51807413,
    "lng": 107644047
  },
  {
    "lat": 51806810,
    "lng": 107643592
  },
  {
    "lat": 51806213,
    "lng": 107643131
  },
  {
    "lat": 51805322,
    "lng": 107642469
  },
  {
    "lat": 51805193,
    "lng": 107642089
  },
  {
    "lat": 51805290,
    "lng": 107640909
  },
  {
    "lat": 51805384,
    "lng": 107639848
  },
  {
    "lat": 51805543,
    "lng": 107637970
  },
  {
    "lat": 51805656,
    "lng": 107636919
  },
  {
    "lat": 51805776,
    "lng": 107635857
  },
  {
    "lat": 51805888,
    "lng": 107634805
  },
  {
    "lat": 51806131,
    "lng": 107632713
  },
  {
    "lat": 51806282,
    "lng": 107631366
  },
  {
    "lat": 51806392,
    "lng": 107630781
  },
  {
    "lat": 51806711,
    "lng": 107629849
  },
  {
    "lat": 51807036,
    "lng": 107628905
  },
  {
    "lat": 51807502,
    "lng": 107627497
  },
  {
    "lat": 51807688,
    "lng": 107626921
  },
  {
    "lat": 51807817,
    "lng": 107626232
  },
  {
    "lat": 51807872,
    "lng": 107625543
  },
  {
    "lat": 51807859,
    "lng": 107624474
  },
  {
    "lat": 51807837,
    "lng": 107623004
  },
  {
    "lat": 51807858,
    "lng": 107622640
  },
  {
    "lat": 51808002,
    "lng": 107621933
  },
  {
    "lat": 51808323,
    "lng": 107620827
  },
  {
    "lat": 51808396,
    "lng": 107620610
  },
  {
    "lat": 51808694,
    "lng": 107619656
  },
  {
    "lat": 51809072,
    "lng": 107618489
  },
  {
    "lat": 51809072,
    "lng": 107618241
  },
  {
    "lat": 51809079,
    "lng": 107616228
  },
  {
    "lat": 51809079,
    "lng": 107615150
  },
  {
    "lat": 51809079,
    "lng": 107614077
  },
  {
    "lat": 51809079,
    "lng": 107613004
  },
  {
    "lat": 51809079,
    "lng": 107611932
  },
  {
    "lat": 51809079,
    "lng": 107610859
  },
  {
    "lat": 51809079,
    "lng": 107609786
  },
  {
    "lat": 51809093,
    "lng": 107608711
  },
  {
    "lat": 51809092,
    "lng": 107607640
  },
  {
    "lat": 51809092,
    "lng": 107606567
  },
  {
    "lat": 51809092,
    "lng": 107605494
  },
  {
    "lat": 51809092,
    "lng": 107604421
  },
  {
    "lat": 51809092,
    "lng": 107603348
  },
  {
    "lat": 51809092,
    "lng": 107602276
  },
  {
    "lat": 51809092,
    "lng": 107601203
  },
  {
    "lat": 51809092,
    "lng": 107600130
  },
  {
    "lat": 51809090,
    "lng": 107598833
  },
  {
    "lat": 51809278,
    "lng": 107598284
  },
  {
    "lat": 51809789,
    "lng": 107597598
  },
  {
    "lat": 51810543,
    "lng": 107596553
  },
  {
    "lat": 51810814,
    "lng": 107596322
  },
  {
    "lat": 51811572,
    "lng": 107595902
  },
  {
    "lat": 51812223,
    "lng": 107595699
  },
  {
    "lat": 51812873,
    "lng": 107595495
  },
  {
    "lat": 51813523,
    "lng": 107595291
  },
  {
    "lat": 51814180,
    "lng": 107595087
  },
  {
    "lat": 51814830,
    "lng": 107594883
  },
  {
    "lat": 51815709,
    "lng": 107594638
  },
  {
    "lat": 51816342,
    "lng": 107594304
  },
  {
    "lat": 51816972,
    "lng": 107593971
  },
  {
    "lat": 51817965,
    "lng": 107593470
  },
  {
    "lat": 51818904,
    "lng": 107593150
  },
  {
    "lat": 51819552,
    "lng": 107592920
  },
  {
    "lat": 51820763,
    "lng": 107592485
  },
  {
    "lat": 51821439,
    "lng": 107592268
  },
  {
    "lat": 51822046,
    "lng": 107592191
  },
  {
    "lat": 51822709,
    "lng": 107592191
  },
  {
    "lat": 51823879,
    "lng": 107592168
  },
  {
    "lat": 51825115,
    "lng": 107591926
  },
  {
    "lat": 51825231,
    "lng": 107591836
  },
  {
    "lat": 51825792,
    "lng": 107591268
  },
  {
    "lat": 51826356,
    "lng": 107590699
  },
  {
    "lat": 51826913,
    "lng": 107590131
  },
  {
    "lat": 51827477,
    "lng": 107589562
  },
  {
    "lat": 51828040,
    "lng": 107588993
  },
  {
    "lat": 51829121,
    "lng": 107587907
  },
  {
    "lat": 51829361,
    "lng": 107587674
  },
  {
    "lat": 51829458,
    "lng": 107587597
  },
  {
    "lat": 51829638,
    "lng": 107587523
  },
  {
    "lat": 51830493,
    "lng": 107587457
  },
  {
    "lat": 51831156,
    "lng": 107587405
  },
  {
    "lat": 51831820,
    "lng": 107587352
  },
  {
    "lat": 51832483,
    "lng": 107587287
  },
  {
    "lat": 51833293,
    "lng": 107587231
  },
  {
    "lat": 51833462,
    "lng": 107587387
  },
  {
    "lat": 51833691,
    "lng": 107587855
  },
  {
    "lat": 51834100,
    "lng": 107588704
  },
  {
    "lat": 51834505,
    "lng": 107589551
  },
  {
    "lat": 51834916,
    "lng": 107590388
  },
  {
    "lat": 51835402,
    "lng": 107591425
  },
  {
    "lat": 51835797,
    "lng": 107592287
  },
  {
    "lat": 51836348,
    "lng": 107593443
  },
  {
    "lat": 51836572,
    "lng": 107593880
  },
  {
    "lat": 51836786,
    "lng": 107594123
  },
  {
    "lat": 51836982,
    "lng": 107594514
  },
  {
    "lat": 51837225,
    "lng": 107594998
  },
  {
    "lat": 51837446,
    "lng": 107595469
  },
  {
    "lat": 51837492,
    "lng": 107595567
  },
  {
    "lat": 51837563,
    "lng": 107595626
  },
  {
    "lat": 51837731,
    "lng": 107595655
  },
  {
    "lat": 51838049,
    "lng": 107595267
  },
  {
    "lat": 51838582,
    "lng": 107594626
  },
  {
    "lat": 51839112,
    "lng": 107593982
  },
  {
    "lat": 51839703,
    "lng": 107593251
  },
  {
    "lat": 51840171,
    "lng": 107592623
  },
  {
    "lat": 51840366,
    "lng": 107592336
  },
  {
    "lat": 51840776,
    "lng": 107591627
  },
  {
    "lat": 51840851,
    "lng": 107591503
  },
  {
    "lat": 51841224,
    "lng": 107590904
  },
  {
    "lat": 51841938,
    "lng": 107589649
  },
  {
    "lat": 51842093,
    "lng": 107589380
  },
  {
    "lat": 51842206,
    "lng": 107589207
  },
  {
    "lat": 51842678,
    "lng": 107588446
  },
  {
    "lat": 51843472,
    "lng": 107587146
  },
  {
    "lat": 51844001,
    "lng": 107586284
  },
  {
    "lat": 51844586,
    "lng": 107585334
  },
  {
    "lat": 51844756,
    "lng": 107585072
  },
  {
    "lat": 51845123,
    "lng": 107584599
  },
  {
    "lat": 51845216,
    "lng": 107584460
  },
  {
    "lat": 51845688,
    "lng": 107583693
  },
  {
    "lat": 51846152,
    "lng": 107582942
  },
  {
    "lat": 51846622,
    "lng": 107582181
  },
  {
    "lat": 51847543,
    "lng": 107580689
  },
  {
    "lat": 51847826,
    "lng": 107580208
  },
  {
    "lat": 51847929,
    "lng": 107580165
  },
  {
    "lat": 51848007,
    "lng": 107580181
  },
  {
    "lat": 51848478,
    "lng": 107580947
  },
  {
    "lat": 51848942,
    "lng": 107581698
  },
  {
    "lat": 51849832,
    "lng": 107583138
  },
  {
    "lat": 51849947,
    "lng": 107583150
  },
  {
    "lat": 51850042,
    "lng": 107583098
  },
  {
    "lat": 51850132,
    "lng": 107583007
  },
  {
    "lat": 51850314,
    "lng": 107582686
  },
  {
    "lat": 51850771,
    "lng": 107581912
  },
  {
    "lat": 51851235,
    "lng": 107581140
  },
  {
    "lat": 51851735,
    "lng": 107580306
  },
  {
    "lat": 51852189,
    "lng": 107579530
  },
  {
    "lat": 51852653,
    "lng": 107578758
  },
  {
    "lat": 51853312,
    "lng": 107577685
  },
  {
    "lat": 51853955,
    "lng": 107576649
  },
  {
    "lat": 51854529,
    "lng": 107575715
  },
  {
    "lat": 51854806,
    "lng": 107575268
  },
  {
    "lat": 51855084,
    "lng": 107574800
  },
  {
    "lat": 51855392,
    "lng": 107574286
  },
  {
    "lat": 51855393,
    "lng": 107574100
  },
  {
    "lat": 51855325,
    "lng": 107573942
  },
  {
    "lat": 51855205,
    "lng": 107573870
  },
  {
    "lat": 51855111,
    "lng": 107573934
  },
  {
    "lat": 51855037,
    "lng": 107574092
  },
  {
    "lat": 51855038,
    "lng": 107574344
  },
  {
    "lat": 51855050,
    "lng": 107574614
  }
]