{"datetime": "06:38:54 01-38-2021", "maxk": 2065592, "anims": [{"id": "99012315", "lon": 107620582, "lat": 51808364, "dir": 119, "lasttime": "31.08.2021 22:38:09", "gos_num": "т55", "rid": 8, "rnum": "2", "rtype": "Тр", "low_floor": "0"}, {"id": "33136953", "lon": 107666336, "lat": 51821538, "dir": 260, "lasttime": "31.08.2021 22:38:37", "gos_num": "т51", "rid": 10, "rnum": "4", "rtype": "Тр", "low_floor": "0"}, {"id": "33136806", "lon": 107609246, "lat": 51809057, "dir": 270, "lasttime": "31.08.2021 22:38:37", "gos_num": "т11", "rid": 10, "rnum": "4", "rtype": "Тр", "low_floor": "0"}, {"id": "99012304", "lon": 107657440, "lat": 51817321, "dir": 182, "lasttime": "31.08.2021 22:38:07", "gos_num": "т49", "rid": 1, "rnum": "1", "rtype": "Тр", "low_floor": "0"}, {"id": "99012303", "lon": 107658088, "lat": 51825271, "dir": 2, "lasttime": "31.08.2021 22:38:17", "gos_num": "т21", "rid": 8, "rnum": "2", "rtype": "Тр", "low_floor": "0"}, {"id": "99012316", "lon": 107618347, "lat": 51809074, "dir": 274, "lasttime": "31.08.2021 22:38:21", "gos_num": "т28", "rid": 1, "rnum": "1", "rtype": "Тр", "low_floor": "0"}, {"id": "99012397", "lon": 107573991, "lat": 51855041, "dir": 136, "lasttime": "31.08.2021 22:38:30", "gos_num": "т93", "rid": 1, "rnum": "1", "rtype": "Тр", "low_floor": "0"}, {"id": "99012491", "lon": 107575154, "lat": 51854836, "dir": 137, "lasttime": "31.08.2021 22:38:09", "gos_num": "т91", "rid": 8, "rnum": "2", "rtype": "Тр", "low_floor": "0"}, {"id": "99012399", "lon": 107649749, "lat": 51821865, "dir": 99, "lasttime": "31.08.2021 22:38:10", "gos_num": "т36", "rid": 9, "rnum": "4", "rtype": "Тр", "low_floor": "0"}, {"id": "47015076", "lon": 107623916, "lat": 51815420, "dir": 184, "lasttime": "31.08.2021 22:38:11", "gos_num": "т05", "rid": 10, "rnum": "4", "rtype": "Тр", "low_floor": "0"}, {"id": "33137020", "lon": 107595459, "lat": 51837431, "dir": 56, "lasttime": "31.08.2021 22:38:37", "gos_num": "т85", "rid": 1, "rnum": "1", "rtype": "Тр", "low_floor": "0"}, {"id": "33121614", "lon": 107613777, "lat": 51841670, "dir": 88, "lasttime": "31.08.2021 22:38:34", "gos_num": "т94", "rid": 10, "rnum": "4", "rtype": "Тр", "low_floor": "0"}, {"id": "47015075", "lon": 107587175, "lat": 51843483, "dir": 315, "lasttime": "31.08.2021 22:38:25", "gos_num": "т04", "rid": 8, "rnum": "2", "rtype": "Тр", "low_floor": "0"}, {"id": "99012330", "lon": 107598182, "lat": 51809402, "dir": 320, "lasttime": "31.08.2021 22:38:14", "gos_num": "т89", "rid": 1, "rnum": "1", "rtype": "Тр", "low_floor": "0"}, {"id": "33137180", "lon": 107595026, "lat": 51814755, "dir": 347, "lasttime": "31.08.2021 22:38:36", "gos_num": "т97", "rid": 10, "rnum": "4", "rtype": "Тр", "low_floor": "0"}, {"id": "33136724", "lon": 107651853, "lat": 51840822, "dir": 344, "lasttime": "31.08.2021 22:38:36", "gos_num": "т78", "rid": 8, "rnum": "2", "rtype": "Тр", "low_floor": "0"}]}