{"datetime": "11:22:42 01-22-2021", "maxk": 2606132, "anims": [{"id": "99012315", "lon": 107575698, "lat": 51854385, "dir": 184, "lasttime": "01.09.2021 03:20:28", "gos_num": "т55", "rid": 8, "rnum": "2", "rtype": "Тр", "low_floor": "0"}, {"id": "33136953", "lon": 107675550, "lat": 51823513, "dir": 272, "lasttime": "01.09.2021 03:22:18", "gos_num": "т51", "rid": 10, "rnum": "4", "rtype": "Тр", "low_floor": "0"}, {"id": "33121607", "lon": 107592653, "lat": 51820175, "dir": 168, "lasttime": "01.09.2021 03:21:56", "gos_num": "т38", "rid": 9, "rnum": "4", "rtype": "Тр", "low_floor": "0"}, {"id": "33137004", "lon": 107582099, "lat": 51846725, "dir": 314, "lasttime": "01.09.2021 03:22:07", "gos_num": "т92", "rid": 1, "rnum": "1", "rtype": "Тр", "low_floor": "0"}, {"id": "33121655", "lon": 107648132, "lat": 51841569, "dir": 104, "lasttime": "01.09.2021 03:22:14", "gos_num": "т25", "rid": 1, "rnum": "1", "rtype": "Тр", "low_floor": "0"}, {"id": "99012321", "lon": 107623222, "lat": 51807830, "dir": 449, "lasttime": "01.09.2021 03:22:05", "gos_num": "т86", "rid": 8, "rnum": "2", "rtype": "Тр", "low_floor": "0"}, {"id": "99012308", "lon": 107589317, "lat": 51842090, "dir": 133, "lasttime": "01.09.2021 03:21:55", "gos_num": "т53", "rid": 8, "rnum": "2", "rtype": "Тр", "low_floor": "0"}, {"id": "99012301", "lon": 107604293, "lat": 51841197, "dir": 81, "lasttime": "01.09.2021 03:22:18", "gos_num": "т19", "rid": 10, "rnum": "4", "rtype": "Тр", "low_floor": "0"}, {"id": "99012397", "lon": 107603956, "lat": 51841196, "dir": 60, "lasttime": "01.09.2021 03:22:19", "gos_num": "т93", "rid": 1, "rnum": "1", "rtype": "Тр", "low_floor": "0"}, {"id": "99012491", "lon": 107589819, "lat": 51827219, "dir": 142, "lasttime": "01.09.2021 03:21:57", "gos_num": "т91", "rid": 8, "rnum": "2", "rtype": "Тр", "low_floor": "0"}, {"id": "99012332", "lon": 107655227, "lat": 51833309, "dir": 344, "lasttime": "01.09.2021 03:22:05", "gos_num": "т77", "rid": 8, "rnum": "2", "rtype": "Тр", "low_floor": "0"}, {"id": "99012306", "lon": 107615798, "lat": 51841625, "dir": 267, "lasttime": "01.09.2021 03:22:14", "gos_num": "т33", "rid": 8, "rnum": "2", "rtype": "Тр", "low_floor": "0"}, {"id": "99012399", "lon": 107604446, "lat": 51841220, "dir": 266, "lasttime": "01.09.2021 03:22:05", "gos_num": "т36", "rid": 9, "rnum": "4", "rtype": "Тр", "low_floor": "0"}, {"id": "99012434", "lon": 107625533, "lat": 51843384, "dir": 159, "lasttime": "01.09.2021 03:22:06", "gos_num": "т34", "rid": 9, "rnum": "4", "rtype": "Тр", "low_floor": "0"}, {"id": "99012429", "lon": 107642694, "lat": 51805394, "dir": 26, "lasttime": "01.09.2021 03:22:00", "gos_num": "т29", "rid": 8, "rnum": "2", "rtype": "Тр", "low_floor": "0"}, {"id": "99012490", "lon": 107595856, "lat": 51811684, "dir": 345, "lasttime": "01.09.2021 03:21:48", "gos_num": "т90", "rid": 10, "rnum": "4", "rtype": "Тр", "low_floor": "0"}, {"id": "47015076", "lon": 107623585, "lat": 51817931, "dir": 165, "lasttime": "01.09.2021 03:21:53", "gos_num": "т05", "rid": 10, "rnum": "4", "rtype": "Тр", "low_floor": "0"}, {"id": "33137020", "lon": 107580233, "lat": 51847995, "dir": 0, "lasttime": "01.09.2021 03:22:19", "gos_num": "т85", "rid": 1, "rnum": "1", "rtype": "Тр", "low_floor": "0"}, {"id": "33121614", "lon": 107649560, "lat": 51821807, "dir": 269, "lasttime": "01.09.2021 03:22:12", "gos_num": "т94", "rid": 10, "rnum": "4", "rtype": "Тр", "low_floor": "0"}, {"id": "47015075", "lon": 107583628, "lat": 51845680, "dir": 141, "lasttime": "01.09.2021 03:22:17", "gos_num": "т04", "rid": 8, "rnum": "2", "rtype": "Тр", "low_floor": "0"}, {"id": "33137180", "lon": 107678925, "lat": 51822801, "dir": 0, "lasttime": "01.09.2021 03:22:17", "gos_num": "т97", "rid": 10, "rnum": "4", "rtype": "Тр", "low_floor": "0"}, {"id": "33001891", "lon": 107597087, "lat": 51810192, "dir": 325, "lasttime": "01.09.2021 03:20:34", "gos_num": "т83", "rid": 1, "rnum": "1", "rtype": "Тр", "low_floor": "0"}, {"id": "33136724", "lon": 107580977, "lat": 51847386, "dir": 291, "lasttime": "01.09.2021 03:22:16", "gos_num": "т78", "rid": 8, "rnum": "2", "rtype": "Тр", "low_floor": "0"}, {"id": "47015084", "lon": 107654120, "lat": 51812201, "dir": 227, "lasttime": "01.09.2021 03:22:02", "gos_num": "т14", "rid": 1, "rnum": "1", "rtype": "Тр", "low_floor": "0"}, {"id": "99012387", "lon": 107634088, "lat": 51805959, "dir": 280, "lasttime": "01.09.2021 03:21:55", "gos_num": "т87", "rid": 1, "rnum": "1", "rtype": "Тр", "low_floor": "0"}, {"id": "47015079", "lon": 107605816, "lat": 51809056, "dir": 90, "lasttime": "01.09.2021 03:22:02", "gos_num": "т08", "rid": 8, "rnum": "2", "rtype": "Тр", "low_floor": "0"}, {"id": "47015074", "lon": 107670565, "lat": 51822183, "dir": 414, "lasttime": "01.09.2021 03:22:20", "gos_num": "т03", "rid": 9, "rnum": "4", "rtype": "Тр", "low_floor": "1"}, {"id": "33145064", "lon": 107588581, "lat": 51842616, "dir": 133, "lasttime": "01.09.2021 03:22:11", "gos_num": "т61", "rid": 1, "rnum": "1", "rtype": "Тр", "low_floor": "0"}, {"id": "47015072", "lon": 107613500, "lat": 51809070, "dir": 270, "lasttime": "01.09.2021 03:22:12", "gos_num": "т01", "rid": 10, "rnum": "4", "rtype": "Тр", "low_floor": "1"}, {"id": "99012430", "lon": 107623579, "lat": 51814204, "dir": 10, "lasttime": "01.09.2021 03:22:04", "gos_num": "т30", "rid": 9, "rnum": "4", "rtype": "Тр", "low_floor": "0"}, {"id": "33137315", "lon": 107587294, "lat": 51831415, "dir": 357, "lasttime": "01.09.2021 03:22:17", "gos_num": "т72", "rid": 10, "rnum": "4", "rtype": "Тр", "low_floor": "0"}]}