{"datetime": "13:25:51 16-25-2021", "maxk": 15109252, "anims": [{"id": "99012399", "lon": 107575347, "lat": 51854911, "dir": 44, "lasttime": "16.11.2021 05:25:14", "gos_num": "т36", "rid": 8, "rnum": "2", "rtype": "Тр", "low_floor": "0"}, {"id": "99012325", "lon": 107589080, "lat": 51834270, "dir": 47, "lasttime": "16.11.2021 05:25:01", "gos_num": "т56", "rid": 10, "rnum": "4", "rtype": "Тр", "low_floor": "0"}, {"id": "99012472", "lon": 107655284, "lat": 51833171, "dir": 162, "lasttime": "16.11.2021 05:24:56", "gos_num": "т72", "rid": 1, "rnum": "1", "rtype": "Тр", "low_floor": "0"}, {"id": "99012438", "lon": 107621164, "lat": 51843973, "dir": 129, "lasttime": "16.11.2021 05:25:17", "gos_num": "т38", "rid": 10, "rnum": "4", "rtype": "Тр", "low_floor": "0"}, {"id": "99012316", "lon": 107599136, "lat": 51809078, "dir": 271, "lasttime": "16.11.2021 05:25:10", "gos_num": "т28", "rid": 10, "rnum": "4", "rtype": "Тр", "low_floor": "0"}, {"id": "99012301", "lon": 107613113, "lat": 51841587, "dir": 86, "lasttime": "16.11.2021 05:25:02", "gos_num": "т19", "rid": 1, "rnum": "1", "rtype": "Тр", "low_floor": "0"}, {"id": "99012315", "lon": 107678367, "lat": 51822917, "dir": 221, "lasttime": "16.11.2021 05:22:50", "gos_num": "т55", "rid": 10, "rnum": "4", "rtype": "Тр", "low_floor": "0"}, {"id": "99012321", "lon": 107649124, "lat": 51821857, "dir": 268, "lasttime": "16.11.2021 05:25:10", "gos_num": "т86", "rid": 10, "rnum": "4", "rtype": "Тр", "low_floor": "0"}, {"id": "99012332", "lon": 107657211, "lat": 51814456, "dir": 362, "lasttime": "16.11.2021 05:25:19", "gos_num": "т77", "rid": 8, "rnum": "2", "rtype": "Тр", "low_floor": "0"}, {"id": "99012448", "lon": 107639029, "lat": 51805458, "dir": 281, "lasttime": "16.11.2021 05:25:27", "gos_num": "т48", "rid": 1, "rnum": "1", "rtype": "Тр", "low_floor": "0"}, {"id": "99012306", "lon": 107622795, "lat": 51812381, "dir": 207, "lasttime": "16.11.2021 05:25:06", "gos_num": "т33", "rid": 10, "rnum": "4", "rtype": "Тр", "low_floor": "0"}, {"id": "99012302", "lon": 107658485, "lat": 51821125, "dir": 93, "lasttime": "16.11.2021 05:25:07", "gos_num": "т45", "rid": 9, "rnum": "4", "rtype": "Тр", "low_floor": "0"}, {"id": "99012308", "lon": 107589683, "lat": 51827362, "dir": 152, "lasttime": "16.11.2021 05:25:07", "gos_num": "т53", "rid": 9, "rnum": "4", "rtype": "Тр", "low_floor": "0"}, {"id": "99012461", "lon": 107578744, "lat": 51852648, "dir": 123, "lasttime": "16.11.2021 05:25:24", "gos_num": "т61", "rid": 1, "rnum": "1", "rtype": "Тр", "low_floor": "0"}, {"id": "99012498", "lon": 107602578, "lat": 51840846, "dir": 231, "lasttime": "16.11.2021 05:24:43", "gos_num": "т98", "rid": 8, "rnum": "2", "rtype": "Тр", "low_floor": "0"}, {"id": "99012488", "lon": 107626121, "lat": 51841349, "dir": 267, "lasttime": "16.11.2021 05:25:33", "gos_num": "т88", "rid": 8, "rnum": "2", "rtype": "Тр", "low_floor": "0"}, {"id": "99012491", "lon": 107596273, "lat": 51837761, "dir": 412, "lasttime": "16.11.2021 05:25:21", "gos_num": "т91", "rid": 1, "rnum": "1", "rtype": "Тр", "low_floor": "0"}, {"id": "99012485", "lon": 107630708, "lat": 51821556, "dir": 449, "lasttime": "16.11.2021 05:25:19", "gos_num": "т85", "rid": 9, "rnum": "4", "rtype": "Тр", "low_floor": "0"}, {"id": "99012397", "lon": 107580296, "lat": 51847748, "dir": 135, "lasttime": "16.11.2021 05:24:43", "gos_num": "т93", "rid": 1, "rnum": "1", "rtype": "Тр", "low_floor": "0"}, {"id": "47015087", "lon": 107656538, "lat": 51830571, "dir": 344, "lasttime": "16.11.2021 05:25:07", "gos_num": "т16", "rid": 8, "rnum": "2", "rtype": "Тр", "low_floor": "1"}, {"id": "99012497", "lon": 107590419, "lat": 51841426, "dir": 313, "lasttime": "16.11.2021 05:24:37", "gos_num": "т97", "rid": 8, "rnum": "2", "rtype": "Тр", "low_floor": "0"}, {"id": "47015072", "lon": 107614910, "lat": 51809046, "dir": 90, "lasttime": "16.11.2021 05:25:06", "gos_num": "т01", "rid": 9, "rnum": "4", "rtype": "Тр", "low_floor": "1"}, {"id": "99012490", "lon": 107595174, "lat": 51814146, "dir": 349, "lasttime": "16.11.2021 05:25:31", "gos_num": "т90", "rid": 1, "rnum": "1", "rtype": "Тр", "low_floor": "0"}, {"id": "99012480", "lon": 107598843, "lat": 51839103, "dir": 232, "lasttime": "16.11.2021 05:24:55", "gos_num": "т80", "rid": 9, "rnum": "4", "rtype": "Тр", "low_floor": "0"}, {"id": "47015075", "lon": 107595460, "lat": 51837365, "dir": 50, "lasttime": "16.11.2021 05:25:07", "gos_num": "т04", "rid": 1, "rnum": "1", "rtype": "Тр", "low_floor": "1"}, {"id": "47015084", "lon": 107630956, "lat": 51806325, "dir": 105, "lasttime": "16.11.2021 05:25:16", "gos_num": "т14", "rid": 8, "rnum": "2", "rtype": "Тр", "low_floor": "1"}, {"id": "99012330", "lon": 107592117, "lat": 51823627, "dir": 171, "lasttime": "16.11.2021 05:24:42", "gos_num": "т89", "rid": 8, "rnum": "2", "rtype": "Тр", "low_floor": "0"}, {"id": "99012492", "lon": 107587084, "lat": 51843478, "dir": 132, "lasttime": "16.11.2021 05:24:52", "gos_num": "т92", "rid": 8, "rnum": "2", "rtype": "Тр", "low_floor": "0"}, {"id": "47015081", "lon": 107578113, "lat": 51853146, "dir": 312, "lasttime": "16.11.2021 05:24:54", "gos_num": "т10", "rid": 1, "rnum": "1", "rtype": "Тр", "low_floor": "1"}, {"id": "47015086", "lon": 107620945, "lat": 51808273, "dir": 297, "lasttime": "16.11.2021 05:25:28", "gos_num": "т15", "rid": 1, "rnum": "1", "rtype": "Тр", "low_floor": "1"}]}